{
  "Abrasives": null,
  "Aluminum": "Al",
  "Antimony": "Sb",
  "Arsenic": "As",
  "Asbestos": null,
  "Barite  ": "Ba",
  "Bauxite": "Al",
  "Beryllium  ": "Be",
  "Bismuth": "Bi",
  "Boron ": "B",
  "Bromine ": "Br",
  "Cadmium ": "Cd",
  "Cement": null,
  "Chromium": "Cr",
  "Clays": null,
  "Cobalt": "Co",
  "Copper ": "Cu",
  "Diamond (industrial)": "C",
  "Diatomite": "Si",
  "Feldspar": "K",
  "Fluorspar": "F",
  "Gallium ": "Ga",
  "Garnet (industrial)": null,
  "Gemanium": "Ge",
  "Gemstones": null,
  "Gold ": "Au",
  "Graphite": "C",
  "Gypsum": "Ca",
  "Helium": "He",
  "Indium": "In",
  "Iodine": "I",
  "Iron Ore  ": "Fe",
  "Iron and Steel": "Fe",
  "Iron oxide pigments": "Fe",
  "Kyanite and Related Minerals": "Al",
  "Lead": "Pb",
  "Lime": "Ca",
  "Lithium ": "Li",
  "Magnesium Compounds": "Mg",
  "Magnesium metal": "Mg",
  "Manganese": "Mn",
  "Mercury": "Hg",
  "Mica (Natural)": "K",
  "Molybdenum ": "Mo",
  "Nickel": ["Ni", "Sc"],
  "Niobium": "Nb",
  "Nitrogen(fixed) - Ammonia": "N",
  "Peat ": "C",
  "Perlite": "Si",
  "Phosphate rock ": "P",
  "Platinum-Group metals": [
    "Pt",
    "Pd",
    "Rh",
    "Ir",
    "Os",
    "Ru"
  ],
  "Potash  ": "K",
  "Pumice & Pumicite ": "Si",
  "Rare earths": [
    "La",
    "Ce",
    "Pr",
    "Nd",
    "Pm",
    "Sm",
    "Eu",
    "Gd",
    "Tb",
    "Dy",
    "Ho",
    "Er",
    "Tm",
    "Yb",
    "Lu",
    "Y",
    "Sc"
  ],
  "Rhenium": "Re",
  "Salt ": "Na",
  "Sand and gravel (industrial)": "Si",
  "Selenium": "Se",
  "Silicon": "Si",
  "Silver": "Ag",
  "Soda ash": "Na",
  "Strontium": "Sr",
  "Sulfur": "S",
  "Talc and Pyrophyllite": "Mg",
  "Talc, crude": "Mg",
  "Tantalum": "Ta",
  "Tellurium": "Te",
  "Tin": "Sn",
  "Titanium & titanium dioxide": "Ti",
  "Titanium Mineral Concentrates": ["Ti", "Sc"],
  "Tungsten ": "W",
  "Vanadium": "V",
  "Vermiculite": "Mg",
  "Wollastonite": "Ca",
  "Zeolites (natural)": "Si",
  "Zinc": "Zn",
  "Zirconium and Hafnium": [
    "Zr",
    "Hf"
  ]
}